pkmg/__init__.py
pkmg/pkmg.py
pkmg/upload.py
pkmg-3.0.7.dist-info/METADATA
pkmg-3.0.7.dist-info/WHEEL
pkmg-3.0.7.dist-info/top_level.txt
pkmg-3.0.7.dist-info/RECORD
