Metadata-Version: 2.1
Name: pkmg
Version: 3.0.7
Summary: pkmg
Home-page: https://github.com/castar2001kr/python.pkmg.git
Author: DaeHyeonGo
Author-email: castar2001kr@naver.com
License: MIT
Platform: UNKNOWN
Classifier: Programming Language :: Python :: 3
Classifier: License :: OSI Approved :: MIT License
Classifier: Operating System :: OS Independent
